{
    "gpio_pins": {
        "power_connections": {
            "5v1_power_rail": {
                "source": "buck_12v_to_5v1",
                "description": "Rail d'alimentation 5.1V depuis buck 12V→5.1V"
            },
            "3v3_power_rail": {
                "source": "buck_5v1_to_3v3",
                "description": "Rail d'alimentation 3.3V depuis buck 5.1V→3.3V"
            },
            "12v_power_rail": {
                "source": "adaptateur_externe",
                "description": "Rail d'alimentation 12V direct depuis l'adaptateur externe"
            }
        },
        "sensors": {
            "temp_humidity": {
                "gpio_pin": null,
                "type": "DHT22",
                "voltage": "3.3V",
                "current": "5mA",
                "power_connection": "3v3_power_rail",
                "description": "Capteur température et humidité DHT22 - NON BRANCHÉ"
            },
            "light": {
                "gpio_pin": null,
                "type": "LDR",
                "voltage": "3.3V",
                "current": "1mA",
                "power_connection": "3v3_power_rail",
                "description": "Capteur de lumière LDR - NON BRANCHÉ"
            },
            "mq2_gas": {
                "gpio_pin": null,
                "type": "MQ2",
                "voltage": "5.1V",
                "current": "150mA",
                "power_connection": "5v1_power_rail",
                "adc_converter": "PCF8591",
                "adc_voltage": "3.3V",
                "adc_current": "10mA",
                "adc_power_connection": "3v3_power_rail",
                "adc_channel": 0,
                "i2c_address": "0x48",
                "description": "Capteur de gaz MQ2 - NON BRANCHÉ"
            },
            "water_level": {
                "trigger_gpio": null,
                "echo_gpio": null,
                "type": "HC-SR04P",
                "voltage": "3.3V",
                "current": "15mA",
                "power_connection": "3v3_power_rail",
                "description": "Capteur niveau d'eau HC-SR04P - NON BRANCHÉ"
            },
            "radiator_temp": {
                "gpio_pin": null,
                "type": "DS18B20",
                "voltage": "3.3V",
                "current": "1mA",
                "power_connection": "3v3_power_rail",
                "description": "Température radiateur DS18B20 - NON BRANCHÉ"
            }
        },
        "actuators": {
            "heating_relay": {
                "gpio_pin": null,
                "type": "relay",
                "voltage": "5.1V",
                "current": "30mA",
                "power_connection": "5v1_power_rail",
                "description": "Relais chauffage - NON BRANCHÉ"
            },
            "humidity_relay": {
                "gpio_pin": null,
                "type": "relay",
                "voltage": "5.1V",
                "current": "30mA",
                "power_connection": "5v1_power_rail",
                "description": "Relais ultrasonic mist - NON BRANCHÉ"
            },
            "feeding_servo": {
                "gpio_pin": null,
                "type": "servo",
                "voltage": "5.1V",
                "current": "100-250mA",
                "frequency": 50,
                "power_connection": "5v1_power_rail",
                "description": "Servo trappe alimentation - NON BRANCHÉ"
            },
            "fan_relay": {
                "gpio_pin": null,
                "type": "relay",
                "voltage": "5.1V",
                "current": "30mA",
                "power_connection": "5v1_power_rail",
                "description": "Relais ventilateurs - NON BRANCHÉ"
            }
        },
        "interfaces": {
            "lcd_st7735": {
                "spi_gpios": {
                    "dc": null,
                    "cs": null,
                    "rst": null
                },
                "backlight_gpio": null,
                "description": "Écran LCD ST7735 - NON BRANCHÉ"
            },
            "rotary_encoder": {
                "clk_gpio": null,
                "dt_gpio": null,
                "sw_gpio": null,
                "description": "Encodeur rotatif - NON BRANCHÉ"
            }
        },
        "pin_assignments": {
            "TEMP_HUMIDITY_PIN": null,
            "LIGHT_SENSOR_PIN": null,
            "LIGHT_RELAY_PIN": null,
            "MQ2_GAS_PIN": null,
            "WATER_LEVEL_TRIGGER_PIN": null,
            "WATER_LEVEL_ECHO_PIN": null,
            "RADIATOR_TEMP_PIN": null,
            "HEATING_RELAY_PIN": null,
            "HUMIDITY_RELAY_PIN": null,
            "FEEDING_SERVO_PIN": null,
            "FAN_RELAY_PIN": null
        }
    }
}
